teizone
