Metadata-Version: 1.0
Name: teizone
Version: 0.0.2
Summary: Add coordinates to TEI zones.
Home-page: http://github.com/umd_mith/teizone
Author: Ed Summers
Author-email: ehs@pobox.com
License: MIT License
Platform: UNKNOWN
